Contagious_NB/Classification.py
Contagious_NB/__init__.py
Contagious_Naive_Bayes-1.0.2.dist-info/LICENSE.txt
Contagious_Naive_Bayes-1.0.2.dist-info/METADATA
Contagious_Naive_Bayes-1.0.2.dist-info/WHEEL
Contagious_Naive_Bayes-1.0.2.dist-info/top_level.txt
Contagious_Naive_Bayes-1.0.2.dist-info/RECORD
