Metadata-Version: 2.1
Name: Contagious-Naive-Bayes
Version: 1.0.2
Summary: The package enables the use of Contagious Naive Bayes to perform classification
Home-page: https://github.com/iEna101/Contagious-NB
Author: Iena Petronella Derks
Author-email: <inekederks1@gmail.com>
License: UNKNOWN
Platform: UNKNOWN
Classifier: Programming Language :: Python :: 3
Classifier: License :: OSI Approved :: MIT License
Classifier: Operating System :: OS Independent
Requires-Python: >=3.6
